feathr/__init__.py
feathr/client.py
feathr/constants.py
feathr/version.py
feathr/datasets/__init__.py
feathr/datasets/constants.py
feathr/datasets/nyc_taxi.py
feathr/datasets/utils.py
feathr/definition/__init__.py
feathr/definition/_materialization_utils.py
feathr/definition/aggregation.py
feathr/definition/anchor.py
feathr/definition/config_helper.py
feathr/definition/dtype.py
feathr/definition/feathrconfig.py
feathr/definition/feature.py
feathr/definition/feature_derivations.py
feathr/definition/lookup_feature.py
feathr/definition/materialization_settings.py
feathr/definition/monitoring_settings.py
feathr/definition/query_feature_list.py
feathr/definition/repo_definitions.py
feathr/definition/settings.py
feathr/definition/sink.py
feathr/definition/source.py
feathr/definition/transformation.py
feathr/definition/typed_key.py
feathr/protobuf/__init__.py
feathr/protobuf/featureValue_pb2.py
feathr/registry/__init__.py
feathr/registry/_feathr_registry_client.py
feathr/registry/_feature_registry_purview.py
feathr/registry/feature_registry.py
feathr/registry/registry_utils.py
feathr/secrets/__init__.py
feathr/secrets/akv_client.py
feathr/spark_provider/__init__.py
feathr/spark_provider/_abc.py
feathr/spark_provider/_databricks_submission.py
feathr/spark_provider/_localspark_submission.py
feathr/spark_provider/_synapse_submission.py
feathr/spark_provider/feathr_configurations.py
feathr/spark_provider/noop-1.0.jar
feathr/udf/__init__.py
feathr/udf/_preprocessing_pyudf_manager.py
feathr/udf/feathr_pyspark_driver_template.py
feathr/utils/__init__.py
feathr/utils/_env_config_reader.py
feathr/utils/_file_utils.py
feathr/utils/config.py
feathr/utils/feature_printer.py
feathr/utils/job_utils.py
feathr/utils/platform.py
feathr/utils/spark_job_params.py
feathrcli/__init__.py
feathrcli/cli.py
feathrcli/data/feathr_user_workspace/feathr_config.yaml
feathrcli/data/feathr_user_workspace/features/agg_features.py
feathrcli/data/feathr_user_workspace/features/non_agg_features.py
feathr-1.0.0.dist-info/METADATA
feathr-1.0.0.dist-info/WHEEL
feathr-1.0.0.dist-info/entry_points.txt
feathr-1.0.0.dist-info/top_level.txt
feathr-1.0.0.dist-info/RECORD
