Metadata-Version: 2.1
Name: feathr
Version: 1.0.0
Summary: An Enterprise-Grade, High Performance Feature Store
Home-page: https://github.com/feathr-ai/feathr
Author-email: feathr-technical-discuss@lists.lfaidata.foundation
Project-URL: Bug Tracker, https://github.com/feathr-ai/feathr/issues
Classifier: Programming Language :: Python :: 3
Classifier: License :: OSI Approved :: Apache Software License
Classifier: Operating System :: OS Independent
Requires-Python: >=3.7
Requires-Dist: click (<=8.1.3)
Requires-Dist: py4j (<=0.10.9.7)
Requires-Dist: loguru (<=0.6.0)
Requires-Dist: pandas
Requires-Dist: redis (<=4.4.0)
Requires-Dist: requests (<=2.28.1)
Requires-Dist: tqdm (<=4.64.1)
Requires-Dist: pyapacheatlas (<=0.14.0)
Requires-Dist: pyhocon (<=0.3.59)
Requires-Dist: pandavro (<=1.7.1)
Requires-Dist: pyyaml (<=6.0)
Requires-Dist: Jinja2 (<=3.1.2)
Requires-Dist: pyarrow (<=9.0.0)
Requires-Dist: pyspark (>=3.1.2)
Requires-Dist: python-snappy (<=0.6.1)
Requires-Dist: deltalake (>=0.6.2)
Requires-Dist: graphlib-backport (<=1.0.3)
Requires-Dist: protobuf (<=3.19.4,>=3.0.0)
Requires-Dist: confluent-kafka (<=1.9.2)
Requires-Dist: databricks-cli (<=0.17.3)
Requires-Dist: avro (<=1.11.1)
Requires-Dist: azure-storage-file-datalake (<=12.5.0)
Requires-Dist: azure-synapse-spark
Requires-Dist: aiohttp (==3.8.3)
Requires-Dist: azure-identity (>=1.8.0)
Requires-Dist: azure-keyvault-secrets (<=4.6.0)
Requires-Dist: azure-core (<=1.22.1)
Requires-Dist: msrest (<=0.6.21)
Requires-Dist: typing-extensions (>=4.2.0)
Provides-Extra: all
Requires-Dist: azure-cli (==2.37.0) ; extra == 'all'
Requires-Dist: scikit-learn ; extra == 'all'
Requires-Dist: pytest-mock (>=3.8.1) ; extra == 'all'
Requires-Dist: jupyter (>=1.0.0) ; extra == 'all'
Requires-Dist: scrapbook (<1.0.0,>=0.5.0) ; extra == 'all'
Requires-Dist: matplotlib (>=3.6.1) ; extra == 'all'
Requires-Dist: pytest-xdist ; extra == 'all'
Requires-Dist: pytest-cov ; extra == 'all'
Requires-Dist: black (>=22.1.0) ; extra == 'all'
Requires-Dist: pytest (>=7) ; extra == 'all'
Requires-Dist: plotly ; extra == 'all'
Requires-Dist: isort ; extra == 'all'
Requires-Dist: papermill (<3,>=2.1.2) ; extra == 'all'
Provides-Extra: dev
Requires-Dist: black (>=22.1.0) ; extra == 'dev'
Requires-Dist: isort ; extra == 'dev'
Requires-Dist: pytest (>=7) ; extra == 'dev'
Requires-Dist: pytest-cov ; extra == 'dev'
Requires-Dist: pytest-xdist ; extra == 'dev'
Requires-Dist: pytest-mock (>=3.8.1) ; extra == 'dev'
Provides-Extra: notebook
Requires-Dist: azure-cli (==2.37.0) ; extra == 'notebook'
Requires-Dist: jupyter (>=1.0.0) ; extra == 'notebook'
Requires-Dist: matplotlib (>=3.6.1) ; extra == 'notebook'
Requires-Dist: papermill (<3,>=2.1.2) ; extra == 'notebook'
Requires-Dist: scrapbook (<1.0.0,>=0.5.0) ; extra == 'notebook'
Requires-Dist: scikit-learn ; extra == 'notebook'
Requires-Dist: plotly ; extra == 'notebook'
